asgineer/__init__.py
asgineer/_app.py
asgineer/_compat.py
asgineer/_request.py
asgineer/_run.py
asgineer/testutils.py
asgineer/utils.py
asgineer-0.9.5.dist-info/licenses/LICENSE
asgineer-0.9.5.dist-info/WHEEL
asgineer-0.9.5.dist-info/METADATA
asgineer-0.9.5.dist-info/RECORD
