Metadata-Version: 2.4
Name: asgineer
Version: 0.9.5
Summary: A really thin ASGI web framework
Keywords: ASGI,web,framework
Author: Almar Klein
Requires-Python: >= 3.8
License-File: LICENSE
Requires-Dist: asgineer[lint, docs, tests] ; extra == "dev"
Requires-Dist: sphinx>7.2 ; extra == "docs"
Requires-Dist: sphinx_rtd_theme ; extra == "docs"
Requires-Dist: ruff ; extra == "lint"
Requires-Dist: pytest ; extra == "tests"
Requires-Dist: pytest-cov ; extra == "tests"
Requires-Dist: requests ; extra == "tests"
Requires-Dist: websockets ; extra == "tests"
Requires-Dist: uvicorn ; extra == "tests"
Requires-Dist: hypercorn ; extra == "tests"
Requires-Dist: daphne ; extra == "tests"
Project-URL: Documentation, https://asgineer.readthedocs.io
Project-URL: Homepage, https://github.com/almarklein/asgineer
Project-URL: Repository, https://github.com/almarklein/asgineer
Provides-Extra: dev
Provides-Extra: docs
Provides-Extra: lint
Provides-Extra: tests
